<?xml version="1.0" encoding="UTF-8"?>
<recenttracks user="tdga">
<track streamable="true">
            <artist mbid="cb67438a-7f50-4f2b-a6f1-2bb2729fd538">Air</artist>
    <name>All I Need</name>
    <mbid></mbid>
    <album mbid="ffde4b16-8ccd-40fa-a97e-87ba841fc5d6">Live BBC Int Shephard's Bush E</album>
    <url>http://www.last.fm/music/Air/_/All+I+Need</url>
                <date uts="1292993080">22 Dec 2010, 04:44</date>
</track>
<track streamable="true">
            <artist mbid="0efe858c-89e5-4e47-906a-356fa953fd6e">Editors</artist>
    <name>Camera</name>
    <mbid></mbid>
    <album mbid="0d0f03e6-3d7b-42df-abd6-3ae22cc6b38d">The Back Room</album>
    <url>http://www.last.fm/music/Editors/_/Camera</url>
                <date uts="1292992801">22 Dec 2010, 04:40</date>
</track>
<track streamable="true">
            <artist mbid="a74b1b7f-71a5-4011-9441-d0b5e4122711">Radiohead</artist>
    <name>Bullet Proof...I Wish I Was</name>
    <mbid></mbid>
    <album mbid="">Album Box Set</album>
    <url>http://www.last.fm/music/Radiohead/_/Bullet+Proof...I+Wish+I+Was</url>
                <date uts="1292992581">22 Dec 2010, 04:36</date>
</track>
<track streamable="true">
            <artist mbid="59a7fbcb-ff74-494d-abd0-9c82359040c9">Grizzly Bear</artist>
    <name>This Song</name>
    <mbid></mbid>
    <album mbid="8e1f5a9f-8819-4586-a973-3b32744b0b02">Horn Of Plenty</album>
    <url>http://www.last.fm/music/Grizzly+Bear/_/This+Song</url>
                <date uts="1292992344">22 Dec 2010, 04:32</date>
</track>
<track streamable="true">
            <artist mbid="40da522c-be33-4510-8f96-6ca479a96bf0">Fleshcrawl</artist>
    <name>Anthem Of Death</name>
    <mbid></mbid>
    <album mbid="ccdfd029-70c2-483c-b3cf-8e93f351110a">Structures Of Death</album>
    <url>http://www.last.fm/music/Fleshcrawl/_/Anthem+Of+Death</url>
                <date uts="1291156708">30 Nov 2010, 22:38</date>
</track>
<track streamable="true">
            <artist mbid="765134ee-706c-4410-a309-caf90c35d168">Armagedda</artist>
    <name>Emperor from the Eternal Dark</name>
    <mbid></mbid>
    <album mbid="652a36d3-a074-429d-b1f9-47e7e63bb74e">Only True Believers</album>
    <url>http://www.last.fm/music/Armagedda/_/Emperor+from+the+Eternal+Dark</url>
                <date uts="1291156589">30 Nov 2010, 22:36</date>
</track>
<track streamable="false">
            <artist mbid="4bde96f1-3813-4169-afd1-949f06feb890">Decrepit Birth</artist>
    <name>The Resonance</name>
    <mbid></mbid>
    <album mbid=""></album>
    <url>http://www.last.fm/music/Decrepit+Birth/_/The+Resonance</url>
                <date uts="1286318015">5 Oct 2010, 22:33</date>
</track>
<track streamable="true">
            <artist mbid="49c15d5f-469e-469c-ae94-89e8d31106dd">Dismember</artist>
    <name>Dreaming in red</name>
    <mbid></mbid>
    <album mbid="3fff0688-caf7-480f-b325-4d98c326b885">Indecent &amp; Obscene</album>
    <url>http://www.last.fm/music/Dismember/_/Dreaming+in+red</url>
                <date uts="1286317576">5 Oct 2010, 22:26</date>
</track>
<track streamable="false">
            <artist mbid="82c3f8ca-5b90-4150-957e-a4c319f6e863">Evol</artist>
    <name>Prologue</name>
    <mbid></mbid>
    <album mbid=""></album>
    <url>http://www.last.fm/music/Evol/_/Prologue</url>
                <date uts="1253504790">21 Sep 2009, 03:46</date>
</track>
<track streamable="false">
            <artist mbid="3ffb996f-6d4f-45ec-a730-d0bef0810840">Austere</artist>
    <name>Towards the great Unknown</name>
    <mbid></mbid>
    <album mbid=""></album>
    <url>http://www.last.fm/music/Austere/_/Towards+the+great+Unknown</url>
                <date uts="1253504019">21 Sep 2009, 03:33</date>
</track>
</recenttracks>