<?xml version="1.0" encoding="UTF-8"?>
<recenttracks user="byoms23">
<track streamable="false">
            <artist mbid="024c3b90-9d09-4c67-902f-fdf49649e4f8">L'Âme Immortelle</artist>
    <name>Phonix</name>
    <mbid></mbid>
    <album mbid=""></album>
    <url>http://www.last.fm/music/L%27%C3%82me+Immortelle/_/Phonix</url>
                <date uts="1304659719">6 May 2011, 05:28</date>
</track>
<track streamable="true">
            <artist mbid="024c3b90-9d09-4c67-902f-fdf49649e4f8">L'Âme Immortelle</artist>
    <name>5 Jahre</name>
    <mbid></mbid>
    <album mbid="1b9136b4-f351-4fd8-be86-029dbf48d74f">Fallen Angel</album>
    <url>http://www.last.fm/music/L%27%C3%82me+Immortelle/_/5+Jahre</url>
                <date uts="1304659465">6 May 2011, 05:24</date>
</track>
<track streamable="false">
            <artist mbid="">Jonna Enckell</artist>
    <name>The Cellae</name>
    <mbid></mbid>
    <album mbid=""></album>
    <url>http://www.last.fm/music/Jonna+Enckell/_/The+Cellae</url>
                <date uts="1304659206">6 May 2011, 05:20</date>
</track>
<track streamable="false">
            <artist mbid="">Jonna Enckell</artist>
    <name>Magic</name>
    <mbid></mbid>
    <album mbid=""></album>
    <url>http://www.last.fm/music/Jonna+Enckell/_/Magic</url>
                <date uts="1304658983">6 May 2011, 05:16</date>
</track>
<track streamable="false">
            <artist mbid="">Jonna Enckell</artist>
    <name>La Scalia Sirenia</name>
    <mbid></mbid>
    <album mbid=""></album>
    <url>http://www.last.fm/music/Jonna+Enckell/_/La+Scalia+Sirenia</url>
                <date uts="1304658730">6 May 2011, 05:12</date>
</track>
<track streamable="false">
            <artist mbid="">Jonna Enckell</artist>
    <name>The Key</name>
    <mbid></mbid>
    <album mbid=""></album>
    <url>http://www.last.fm/music/Jonna+Enckell/_/The+Key</url>
                <date uts="1304658473">6 May 2011, 05:07</date>
</track>
<track streamable="true">
            <artist mbid="">Jonna Enckell</artist>
    <name>I'm Missing</name>
    <mbid></mbid>
    <album mbid="">Piano Sparkling</album>
    <url>http://www.last.fm/music/Jonna+Enckell/_/I%27m+Missing</url>
                <date uts="1304658229">6 May 2011, 05:03</date>
</track>
<track streamable="true">
            <artist mbid="">Jonna Enckell</artist>
    <name>The Silver Tree</name>
    <mbid></mbid>
    <album mbid="">Piano Sparkling</album>
    <url>http://www.last.fm/music/Jonna+Enckell/_/The+Silver+Tree</url>
                <date uts="1304658111">6 May 2011, 05:01</date>
</track>
<track streamable="true">
            <artist mbid="">Jonna Enckell</artist>
    <name>Electric Heart</name>
    <mbid></mbid>
    <album mbid="">Piano Sparkling</album>
    <url>http://www.last.fm/music/Jonna+Enckell/_/Electric+Heart</url>
                <date uts="1304657920">6 May 2011, 04:58</date>
</track>
<track streamable="true">
            <artist mbid="">Jonna Enckell</artist>
    <name>Making Of A Love Poem</name>
    <mbid></mbid>
    <album mbid="">Piano Sparkling</album>
    <url>http://www.last.fm/music/Jonna+Enckell/_/Making+Of+A+Love+Poem</url>
                <date uts="1304656921">6 May 2011, 04:42</date>
</track>
</recenttracks>